<configuration>

    <property>
      <name>yarn.scheduler.capacity.default.minimum-user-limit-percent</name>
      <value>100</value>
    </property>

    <property>
      <name>yarn.scheduler.capacity.maximum-am-resource-percent</name>
      <value>0.4</value>
    </property>

    <property>
      <name>yarn.scheduler.capacity.maximum-applications</name>
      <value>10000</value>
    </property>

    <property>
      <name>yarn.scheduler.capacity.node-locality-delay</name>
      <value>40</value>
    </property>

    <property>
      <name>yarn.scheduler.capacity.root.acl_administer_queue</name>
      <value>*</value>
    </property>

    <property>
      <name>yarn.scheduler.capacity.root.capacity</name>
      <value>100</value>
    </property>

    <property>
      <name>yarn.scheduler.capacity.root.default.acl_administer_jobs</name>
      <value>*</value>
    </property>

    <property>
      <name>yarn.scheduler.capacity.root.default.acl_submit_applications</name>
      <value>*</value>
    </property>

    <property>
      <name>yarn.scheduler.capacity.root.default.capacity</name>
      <value>100</value>
    </property>

    <property>
      <name>yarn.scheduler.capacity.root.default.maximum-capacity</name>
      <value>100</value>
    </property>

    <property>
      <name>yarn.scheduler.capacity.root.default.state</name>
      <value>RUNNING</value>
    </property>

    <property>
      <name>yarn.scheduler.capacity.root.default.user-limit-factor</name>
      <value>1</value>
    </property>

    <property>
      <name>yarn.scheduler.capacity.root.queues</name>
      <value>default</value>
    </property>

  </configuration>
